ojuara.py
emily_pypi-1.0.dist-info/METADATA
emily_pypi-1.0.dist-info/WHEEL
emily_pypi-1.0.dist-info/top_level.txt
emily_pypi-1.0.dist-info/RECORD
