Metadata-Version: 2.1
Name: emily-pypi
Version: 1.0
Summary: Brincando com distribuição python
Home-page: UNKNOWN
Author: Ojuara Abaporojucaíba
Author-email: ojuara@araujo.com
License: UNKNOWN
Platform: UNKNOWN
